<?xml version="1.0" encoding="utf-8"?>
<Document>
  <Engineering version="V18" />
  <SW.Blocks.GlobalDB ID="0">
    <AttributeList>
      <AutoNumber>true</AutoNumber>
      <DBAccessibleFromOPCUA>true</DBAccessibleFromOPCUA>
      <HeaderAuthor />
      <HeaderFamily />
      <HeaderName />
      <HeaderVersion>0.1</HeaderVersion>
      <Interface><Sections xmlns="http://www.siemens.com/automation/Openness/SW/Interface/v5">
  <Section Name="Static">
    <Member Name="DB" Datatype="&quot;typeDefectsDB&quot;" Remanence="NonRetain" Accessibility="Public">
      <AttributeList>
        <BooleanAttribute Name="ExternalAccessible" SystemDefined="true">true</BooleanAttribute>
        <BooleanAttribute Name="ExternalVisible" SystemDefined="true">true</BooleanAttribute>
        <BooleanAttribute Name="ExternalWritable" SystemDefined="true">true</BooleanAttribute>
        <BooleanAttribute Name="SetPoint" SystemDefined="true">false</BooleanAttribute>
      </AttributeList>
      <Sections>
        <Section Name="None">
          <Member Name="i" Datatype="Int" />
          <Member Name="N" Datatype="Int" />
          <Member Name="N_max" Datatype="Int" />
          <Member Name="pos_AR" Datatype="Array[1..30] of &quot;typePositions&quot;">
            <Sections>
              <Section Name="None">
                <Member Name="M1Z" Datatype="Real" />
                <Member Name="M2Y" Datatype="Real" />
                <Member Name="M3X" Datatype="Real" />
                <Member Name="M4O1" Datatype="Real" />
                <Member Name="M5O2" Datatype="Real" />
              </Section>
            </Sections>
          </Member>
        </Section>
      </Sections>
    </Member>
  </Section>
</Sections></Interface>
      <IsOnlyStoredInLoadMemory>false</IsOnlyStoredInLoadMemory>
      <IsRetainMemResEnabled>false</IsRetainMemResEnabled>
      <IsWriteProtectedInAS>false</IsWriteProtectedInAS>
      <MemoryLayout>Optimized</MemoryLayout>
      <MemoryReserve>100</MemoryReserve>
      <Name>_DEFECT_DB</Name>
      <Namespace />
      <Number>44</Number>
      <ProgrammingLanguage>DB</ProgrammingLanguage>
    </AttributeList>
    <ObjectList>
      <MultilingualText ID="1" CompositionName="Comment">
        <ObjectList>
          <MultilingualTextItem ID="2" CompositionName="Items">
            <AttributeList>
              <Culture>en-US</Culture>
              <Text />
            </AttributeList>
          </MultilingualTextItem>
        </ObjectList>
      </MultilingualText>
      <MultilingualText ID="3" CompositionName="Title">
        <ObjectList>
          <MultilingualTextItem ID="4" CompositionName="Items">
            <AttributeList>
              <Culture>en-US</Culture>
              <Text />
            </AttributeList>
          </MultilingualTextItem>
        </ObjectList>
      </MultilingualText>
    </ObjectList>
  </SW.Blocks.GlobalDB>
</Document>